README.rst
setup.py
examples/__init__.py
examples/echo.py
examples/benchmarks/__init__.py
examples/benchmarks/base.py
examples/benchmarks/req_res.py
examples/pub_sub/__init__.py
examples/pub_sub/pub_client.py
examples/pub_sub/pub_server.py
examples/req_res/__init__.py
examples/req_res/client.py
examples/req_res/service.py
examples/req_res/sugar_service.py
examples/taskqueue/__init__.py
examples/taskqueue/multi.py
examples/taskqueue/proxy.py
examples/taskqueue/standalone.py
omnomnom/__init__.py
omnomnom/exceptions.py
omnomnom/handlers.py
omnomnom/models.py
omnomnom/result_backends.py
omnomnom/utils.py
omnomnom.egg-info/PKG-INFO
omnomnom.egg-info/SOURCES.txt
omnomnom.egg-info/dependency_links.txt
omnomnom.egg-info/entry_points.txt
omnomnom.egg-info/not-zip-safe
omnomnom.egg-info/requires.txt
omnomnom.egg-info/top_level.txt
omnomnom/generics/__init__.py
omnomnom/generics/micro/__init__.py
omnomnom/generics/micro/client.py
omnomnom/generics/micro/marshalling.py
omnomnom/generics/micro/service.py
omnomnom/generics/micro/utils.py
omnomnom/generics/taskqueue/__init__.py
omnomnom/generics/taskqueue/client.py
omnomnom/generics/taskqueue/queue.py
omnomnom/generics/taskqueue/worker.py
omnomnom/runners/__init__.py
omnomnom/runners/run_queue.py
omnomnom/runners/run_service.py
omnomnom/runners/run_worker.py